tomation/__init__.py
Tomation-0.1.5.dist-info/LICENSE
Tomation-0.1.5.dist-info/METADATA
Tomation-0.1.5.dist-info/WHEEL
Tomation-0.1.5.dist-info/top_level.txt
Tomation-0.1.5.dist-info/RECORD
