Metadata-Version: 2.1
Name: Tomation
Version: 0.1.5
Summary: Automation library for small or big tasks.
Home-page: 
Author: Eekk2k2
Author-email: eekk2k2@gmail.com
Keywords: Task Automation
Classifier: Programming Language :: Python :: 3
Classifier: License :: OSI Approved :: MIT License
Classifier: Operating System :: Microsoft :: Windows :: Windows 10
License-File: LICENSE
Requires-Dist: pyautogui
Requires-Dist: psutil
Requires-Dist: win32
Requires-Dist: PIL
Requires-Dist: selenium
Requires-Dist: webdriver-manager
Requires-Dist: bs4
Requires-Dist: os
Requires-Dist: sys
Requires-Dist: re
Requires-Dist: numpy
